gatekeeper/__init__.py
gatekeeper/admin.py
gatekeeper/admin_helpers.py
gatekeeper/mixins.py
gatekeeper/models.py
gatekeeper/utils.py
gatekeeper/view_utils.py
gatekeeper/tests/__init__.py
gatekeeper/tests/models.py
gatekeeper/tests/settings.py
gatekeeper/tests/test_article.py
gatekeeper/tests/test_homepage.py
gatekeeper/tests/test_views.py
gatekeeper/tests/urls.py
django_model_gatekeeper-0.1.7.dist-info/LICENSE
django_model_gatekeeper-0.1.7.dist-info/METADATA
django_model_gatekeeper-0.1.7.dist-info/WHEEL
django_model_gatekeeper-0.1.7.dist-info/top_level.txt
django_model_gatekeeper-0.1.7.dist-info/RECORD
